nvsmi.py
nvsmi-0.4.1.dist-info/entry_points.txt
nvsmi-0.4.1.dist-info/LICENSE.txt
nvsmi-0.4.1.dist-info/WHEEL
nvsmi-0.4.1.dist-info/METADATA
nvsmi-0.4.1.dist-info/RECORD
