Metadata-Version: 2.1
Name: nvsmi
Version: 0.4.1
Summary: A (user-)friendly wrapper to nvidia-smi
Home-page: https://github.com/pmav99/nvsmi
License: MIT
Keywords: packaging,dependency,poetry
Author: Panos Mavrogiorgos
Author-email: pmav99@gmail.com
Requires-Python: >=3.6,<3.7
Classifier: Environment :: Console
Classifier: Intended Audience :: Developers
Classifier: Intended Audience :: System Administrators
Classifier: License :: OSI Approved :: MIT License
Classifier: Operating System :: POSIX :: Linux
Classifier: Programming Language :: Python :: 3
Classifier: Programming Language :: Python :: 3.6
Classifier: Topic :: Software Development :: Libraries :: Python Modules
Classifier: Topic :: System :: Hardware :: Hardware Drivers
Classifier: Topic :: Terminals
Classifier: Topic :: Utilities
Project-URL: Documentation, https://github.com/pmav99/nvsmi
Project-URL: Repository, https://github.com/pmav99/nvsmi
